platform_agent/__init__.py
platform_agent/__main__.py
platform_agent/agent_api.py
platform_agent/agent_websocket.py
platform_agent/cmd/__init__.py
platform_agent/cmd/iptables.py
platform_agent/cmd/lsmod.py
platform_agent/cmd/wg_info.py
platform_agent/cmd/wg_show.py
platform_agent/config/__init__.py
platform_agent/config/logger.py
platform_agent/config/settings.py
platform_agent/docker_api/__init__.py
platform_agent/docker_api/docker_api.py
platform_agent/docker_api/helpers.py
platform_agent/executors/__init__.py
platform_agent/executors/batch_send.py
platform_agent/executors/wg_exec.py
platform_agent/files/__init__.py
platform_agent/files/tmp_files.py
platform_agent/lib/__init__.py
platform_agent/lib/ctime.py
platform_agent/lib/dns_resolver.py
platform_agent/lib/file_helper.py
platform_agent/lib/get_info.py
platform_agent/lib/rt_table.py
platform_agent/network/__init__.py
platform_agent/network/autoping.py
platform_agent/network/dummy_watcher.py
platform_agent/network/exporter.py
platform_agent/network/iface_watcher.py
platform_agent/network/iperf.py
platform_agent/network/kubernetes_watcher.py
platform_agent/network/network_info.py
platform_agent/rerouting/__init__.py
platform_agent/rerouting/rerouting.py
platform_agent/routes/__init__.py
platform_agent/routes/routes.py
platform_agent/wireguard/__init__.py
platform_agent/wireguard/helpers.py
platform_agent/wireguard/peer_data_collector.py
platform_agent/wireguard/peer_watcher.py
platform_agent/wireguard/wg_conf.py
tests/__init__.py
tests/conftest.py
tests/test_agent_api.py
tests/test_tmp_files.py
tests/test_wg_conf.py
tests/test_wg_info.py
syntropy_agent-0.0.95.dist-info/LICENSE
syntropy_agent-0.0.95.dist-info/METADATA
syntropy_agent-0.0.95.dist-info/WHEEL
syntropy_agent-0.0.95.dist-info/entry_points.txt
syntropy_agent-0.0.95.dist-info/top_level.txt
syntropy_agent-0.0.95.dist-info/RECORD
